<?xml version="1.0" encoding="utf-8"?>
<xd:acceleratorMap xmlns:xd="http://www.xilinx.com/xidane" xd:functionName="hash_table_top" xd:componentRef="hash_table" xd:initiationInterval="55" xd:clockPeriod="6.400" xd:sequential="true" xd:hostMachine="64" xd:reset="control">
  <xd:arg xd:name="s_axis_lup_req.key" xd:originalName="s_axis_lup_req" xd:direction="in" xd:interfaceRef="s_axis_lup_req_V" xd:busTypeRef="axis" xd:dataPack="true" xd:bitMapping="63:0" xd:dataWidth="64"/>
  <xd:arg xd:name="s_axis_lup_req.source" xd:originalName="s_axis_lup_req" xd:direction="in" xd:interfaceRef="s_axis_lup_req_V" xd:busTypeRef="axis" xd:dataPack="true" xd:bitMapping="64:64" xd:dataWidth="1"/>
  <xd:arg xd:name="s_axis_upd_req.op" xd:originalName="s_axis_upd_req" xd:direction="in" xd:interfaceRef="s_axis_upd_req_V" xd:busTypeRef="axis" xd:dataPack="true" xd:bitMapping="0:0" xd:dataWidth="1"/>
  <xd:arg xd:name="s_axis_upd_req.key" xd:originalName="s_axis_upd_req" xd:direction="in" xd:interfaceRef="s_axis_upd_req_V" xd:busTypeRef="axis" xd:dataPack="true" xd:bitMapping="64:1" xd:dataWidth="64"/>
  <xd:arg xd:name="s_axis_upd_req.value" xd:originalName="s_axis_upd_req" xd:direction="in" xd:interfaceRef="s_axis_upd_req_V" xd:busTypeRef="axis" xd:dataPack="true" xd:bitMapping="80:65" xd:dataWidth="16"/>
  <xd:arg xd:name="s_axis_upd_req.source" xd:originalName="s_axis_upd_req" xd:direction="in" xd:interfaceRef="s_axis_upd_req_V" xd:busTypeRef="axis" xd:dataPack="true" xd:bitMapping="81:81" xd:dataWidth="1"/>
  <xd:arg xd:name="m_axis_lup_rsp.key" xd:originalName="m_axis_lup_rsp" xd:direction="out" xd:interfaceRef="m_axis_lup_rsp_V" xd:busTypeRef="axis" xd:dataPack="true" xd:bitMapping="63:0" xd:dataWidth="64"/>
  <xd:arg xd:name="m_axis_lup_rsp.value" xd:originalName="m_axis_lup_rsp" xd:direction="out" xd:interfaceRef="m_axis_lup_rsp_V" xd:busTypeRef="axis" xd:dataPack="true" xd:bitMapping="79:64" xd:dataWidth="16"/>
  <xd:arg xd:name="m_axis_lup_rsp.hit" xd:originalName="m_axis_lup_rsp" xd:direction="out" xd:interfaceRef="m_axis_lup_rsp_V" xd:busTypeRef="axis" xd:dataPack="true" xd:bitMapping="80:80" xd:dataWidth="1"/>
  <xd:arg xd:name="m_axis_lup_rsp.source" xd:originalName="m_axis_lup_rsp" xd:direction="out" xd:interfaceRef="m_axis_lup_rsp_V" xd:busTypeRef="axis" xd:dataPack="true" xd:bitMapping="81:81" xd:dataWidth="1"/>
  <xd:arg xd:name="m_axis_upd_rsp.op" xd:originalName="m_axis_upd_rsp" xd:direction="out" xd:interfaceRef="m_axis_upd_rsp_V" xd:busTypeRef="axis" xd:dataPack="true" xd:bitMapping="0:0" xd:dataWidth="1"/>
  <xd:arg xd:name="m_axis_upd_rsp.key" xd:originalName="m_axis_upd_rsp" xd:direction="out" xd:interfaceRef="m_axis_upd_rsp_V" xd:busTypeRef="axis" xd:dataPack="true" xd:bitMapping="64:1" xd:dataWidth="64"/>
  <xd:arg xd:name="m_axis_upd_rsp.value" xd:originalName="m_axis_upd_rsp" xd:direction="out" xd:interfaceRef="m_axis_upd_rsp_V" xd:busTypeRef="axis" xd:dataPack="true" xd:bitMapping="80:65" xd:dataWidth="16"/>
  <xd:arg xd:name="m_axis_upd_rsp.success" xd:originalName="m_axis_upd_rsp" xd:direction="out" xd:interfaceRef="m_axis_upd_rsp_V" xd:busTypeRef="axis" xd:dataPack="true" xd:bitMapping="81:81" xd:dataWidth="1"/>
  <xd:arg xd:name="m_axis_upd_rsp.source" xd:originalName="m_axis_upd_rsp" xd:direction="out" xd:interfaceRef="m_axis_upd_rsp_V" xd:busTypeRef="axis" xd:dataPack="true" xd:bitMapping="82:82" xd:dataWidth="1"/>
  <xd:arg xd:name="regInsertFailureCount" xd:originalName="regInsertFailureCount" xd:direction="out" xd:interfaceRef="regInsertFailureCount_V" xd:busTypeRef="register" xd:handshakeRef="ap_vld" xd:dataWidth="16" xd:firstOut="0"/>
  <xd:latencyEstimates xd:best-case="1" xd:worst-case="54" xd:average-case="7"/>
  <xd:resourceEstimates xd:LUT="12418" xd:FF="4528" xd:BRAM="36" xd:DSP="0"/>
</xd:acceleratorMap>
